[
  {
    "type": "namespace_declaration",
    "named": true,
    "fields": {
      "name": {
        "multiple": false,
        "required": true,
        "types": [
          {
            "type": "identifier",
            "named": true
          }
        ]
      }
    }
  },
  {
    "type": "source_file",
    "named": true,
    "root": true,
    "fields": {},
    "children": {
      "multiple": true,
      "required": false,
      "types": [
        {
          "type": "namespace_declaration",
          "named": true
        }
      ]
    }
  },
  {
    "type": ";",
    "named": false
  },
  {
    "type": "identifier",
    "named": true
  },
  {
    "type": "namespace",
    "named": false
  }
]